kvat/__init__.py
kvat/__main__.py
kvat/cli.py
kvat/core/__init__.py
kvat/core/metrics.py
kvat/core/planner.py
kvat/core/profiles.py
kvat/core/report.py
kvat/core/schema.py
kvat/core/search.py
kvat/engines/__init__.py
kvat/engines/base.py
kvat/engines/transformers.py
kvat/probes/__init__.py
kvat/probes/cpu.py
kvat/probes/gpu.py
kvat-0.1.4.dist-info/METADATA
kvat-0.1.4.dist-info/WHEEL
kvat-0.1.4.dist-info/entry_points.txt
kvat-0.1.4.dist-info/licenses/LICENSE
kvat-0.1.4.dist-info/RECORD
