Metadata-Version: 2.4
Name: kvat
Version: 0.1.4
Summary: Automatic KV-cache optimization for HuggingFace Transformers - Find the optimal cache strategy, attention backend, and configuration for your model and hardware.
Project-URL: Homepage, https://github.com/Keyvanhardani/kvcache-autotune
Project-URL: Documentation, https://github.com/Keyvanhardani/kvcache-autotune#readme
Project-URL: Repository, https://github.com/Keyvanhardani/kvcache-autotune
Project-URL: Issues, https://github.com/Keyvanhardani/kvcache-autotune/issues
Author: KVCache Auto-Tuner Contributors
License-Expression: Apache-2.0
License-File: LICENSE
Keywords: deep-learning,flash-attention,huggingface,inference,kv-cache,llm,machine-learning,optimization,pytorch,transformers
Classifier: Development Status :: 4 - Beta
Classifier: Intended Audience :: Developers
Classifier: Intended Audience :: Science/Research
Classifier: License :: OSI Approved :: Apache Software License
Classifier: Operating System :: OS Independent
Classifier: Programming Language :: Python :: 3
Classifier: Programming Language :: Python :: 3.9
Classifier: Programming Language :: Python :: 3.10
Classifier: Programming Language :: Python :: 3.11
Classifier: Programming Language :: Python :: 3.12
Classifier: Topic :: Scientific/Engineering :: Artificial Intelligence
Classifier: Topic :: Software Development :: Libraries :: Python Modules
Requires-Python: >=3.9
Requires-Dist: pydantic>=2.0.0
Requires-Dist: rich>=13.0.0
Requires-Dist: typer>=0.9.0
Provides-Extra: dev
Requires-Dist: mypy>=1.5.0; extra == 'dev'
Requires-Dist: pre-commit>=3.0.0; extra == 'dev'
Requires-Dist: pytest-asyncio>=0.21.0; extra == 'dev'
Requires-Dist: pytest-cov>=4.0.0; extra == 'dev'
Requires-Dist: pytest>=7.0.0; extra == 'dev'
Requires-Dist: ruff>=0.1.0; extra == 'dev'
Provides-Extra: docs
Requires-Dist: mkdocs-material>=9.0.0; extra == 'docs'
Requires-Dist: mkdocs>=1.5.0; extra == 'docs'
Requires-Dist: mkdocstrings[python]>=0.24.0; extra == 'docs'
Provides-Extra: full
Requires-Dist: accelerate>=0.25.0; extra == 'full'
Requires-Dist: psutil>=5.9.0; extra == 'full'
Requires-Dist: pynvml>=11.5.0; extra == 'full'
Requires-Dist: torch>=2.0.0; extra == 'full'
Requires-Dist: transformers>=4.35.0; extra == 'full'
Provides-Extra: transformers
Requires-Dist: accelerate>=0.25.0; extra == 'transformers'
Requires-Dist: torch>=2.0.0; extra == 'transformers'
Requires-Dist: transformers>=4.35.0; extra == 'transformers'
